board_game_bot/__init__.py
board_game_bot/mastodon.py
board_game_bot/twitter.py
board_game_bot/utils.py
board_game_bot-0.4.0.dist-info/LICENSE
board_game_bot-0.4.0.dist-info/WHEEL
board_game_bot-0.4.0.dist-info/METADATA
board_game_bot-0.4.0.dist-info/RECORD
